README.md
setup.py
yahoo_finance_api2/__init__.py
yahoo_finance_api2/exceptions.py
yahoo_finance_api2/share.py
yahoo_finance_api2.egg-info/PKG-INFO
yahoo_finance_api2.egg-info/SOURCES.txt
yahoo_finance_api2.egg-info/dependency_links.txt
yahoo_finance_api2.egg-info/requires.txt
yahoo_finance_api2.egg-info/top_level.txt