Metadata-Version: 2.1
Name: yahoo-finance-api2
Version: 0.0.8
Summary: Yahooo Finance API package
Home-page: https://github.com/pkout/yahoo_finance_api2
Author: Petr Kout
License: UNKNOWN
Platform: UNKNOWN
Classifier: Programming Language :: Python :: 3
Classifier: License :: OSI Approved :: MIT License
Classifier: Operating System :: OS Independent
